paichat/__init__.py
paichat/config.py
paichat/main.py
paichat/openchat.py
paichat/prompt.py
paichat-1.0.2.dist-info/LICENSE
paichat-1.0.2.dist-info/WHEEL
paichat-1.0.2.dist-info/entry_points.txt
paichat-1.0.2.dist-info/METADATA
paichat-1.0.2.dist-info/RECORD
